.testr.conf
AUTHORS
ChangeLog
HACKING.rst
LICENSE
MANIFEST.in
README.rst
openstack-common.conf
requirements.txt
run_tests.sh
setup.cfg
setup.py
test-requirements.txt
tox.ini
doc/source/api.rst
doc/source/conf.py
doc/source/index.rst
doc/source/_templates/sidebarlinks.html
doc/source/_theme_rtd/layout.html
doc/source/_theme_rtd/theme.conf
python_savannaclient.egg-info/PKG-INFO
python_savannaclient.egg-info/SOURCES.txt
python_savannaclient.egg-info/dependency_links.txt
python_savannaclient.egg-info/entry_points.txt
python_savannaclient.egg-info/not-zip-safe
python_savannaclient.egg-info/requires.txt
python_savannaclient.egg-info/top_level.txt
savannaclient/__init__.py
savannaclient/client.py
savannaclient/shell.py
savannaclient/version.py
savannaclient/api/__init__.py
savannaclient/api/base.py
savannaclient/api/client.py
savannaclient/api/cluster_templates.py
savannaclient/api/clusters.py
savannaclient/api/data_sources.py
savannaclient/api/helpers.py
savannaclient/api/httpclient.py
savannaclient/api/images.py
savannaclient/api/job_binaries.py
savannaclient/api/job_binary_internals.py
savannaclient/api/job_executions.py
savannaclient/api/jobs.py
savannaclient/api/node_group_templates.py
savannaclient/api/parameters.py
savannaclient/api/plugins.py
savannaclient/api/shell.py
savannaclient/nova/__init__.py
savannaclient/nova/auth_plugin.py
savannaclient/nova/base.py
savannaclient/nova/extension.py
savannaclient/nova/utils.py
savannaclient/openstack/__init__.py
savannaclient/openstack/common/__init__.py
savannaclient/openstack/common/cliutils.py
savannaclient/openstack/common/gettextutils.py
savannaclient/openstack/common/importutils.py
savannaclient/openstack/common/strutils.py
savannaclient/openstack/common/uuidutils.py
savannaclient/openstack/common/apiclient/__init__.py
savannaclient/openstack/common/apiclient/auth.py
savannaclient/openstack/common/apiclient/base.py
savannaclient/openstack/common/apiclient/client.py
savannaclient/openstack/common/apiclient/exceptions.py
savannaclient/openstack/common/apiclient/fake_client.py
savannaclient/tests/__init__.py
savannaclient/tests/test_resource.py
savannaclient/tests/nova/__init__.py
savannaclient/tests/nova/test_shell.py
savannaclient/tests/nova/utils.py
tools/install_venv.py
tools/install_venv_common.py
tools/with_venv.sh